{
    "IMG-ID": "/mnt/data1/raiyan/breast_cancer/datasets/dmid/png_images/all_images/IMG377.png",
    "BREAST-COMPOSITION": "Fatty with scattered fibroglandular densities",
    "BIRADS": 4,
    "FINDINGS": [
        {
            "Type": "Calcifications",
            "Description": "Fine granular calcifications in the upper outer quadrant."
        },
        {
            "Type": "Mass",
            "Description": "A 10 mm round mass with irregular margins in the lower inner quadrant, no spiculation or microcalcifications noted."
        }
    ]
}